murakami/__init__.py
murakami/__main__.py
murakami/defaults.py
murakami/errors.py
murakami/exporter.py
murakami/exporters/gcs.py
murakami/exporters/local.py
murakami/exporters/scp.py
murakami/runner.py
murakami/runners/dash.py
murakami/runners/libndt5.py
murakami/runners/libndt7.py
murakami/runners/speedtest.py
murakami/server.py
murakami/thing.py
murakami/utils.py
murakami-0.1.0.dist-info/entry_points.txt
murakami-0.1.0.dist-info/LICENSE
murakami-0.1.0.dist-info/WHEEL
murakami-0.1.0.dist-info/METADATA
murakami-0.1.0.dist-info/RECORD
