Metadata-Version: 2.1
Name: murakami
Version: 0.1.0
Summary: A webthings-compliant network measurement tool from M-Lab.
Home-page: https://github.com/throneless-tech/murakami
License: Apache-2.0
Author: Josh King
Author-email: josh@throneless.tech
Requires-Python: >=3.6,<4.0
Classifier: License :: OSI Approved :: Apache Software License
Classifier: Programming Language :: Python :: 3
Classifier: Programming Language :: Python :: 3.6
Classifier: Programming Language :: Python :: 3.7
Requires-Dist: apscheduler (>=3.6,<4.0)
Requires-Dist: configargparse (>=0.14.0,<0.15.0)
Requires-Dist: jsonlines (>=1.2,<2.0)
Requires-Dist: livejson (>=1.8,<2.0)
Requires-Dist: paramiko (>=2.6,<3.0)
Requires-Dist: scp (>=0.13.2,<0.14.0)
Requires-Dist: tomlkit (>=0.5.5,<0.6.0)
Requires-Dist: webthing (>=0.12.0,<0.13.0)
Project-URL: Repository, https://github.com/throneless-tech/murakami
